<launch4jConfig>
  <dontWrapJar>false</dontWrapJar>
  <headerType>gui</headerType>
  <jar>C:\workspace\RepDev\com\repdev\launcher\launcher.jar</jar>
  <outfile>C:\workspace\RepDev\repdev.exe</outfile>
  <errTitle></errTitle>
  <cmdLine>--log</cmdLine>
  <chdir></chdir>
  <priority>normal</priority>
  <downloadUrl>http://java.com/download</downloadUrl>
  <supportUrl></supportUrl>
  <customProcName>true</customProcName>
  <stayAlive>false</stayAlive>
  <manifest></manifest>
  <icon>C:\workspace\RepDev\repdev-icons\monkeyIcon32.ico</icon>
  <jre>
    <path></path>
    <minVersion>1.5.0</minVersion>
    <maxVersion></maxVersion>
    <jdkPreference>preferJdk</jdkPreference>
    <initialHeapSize>128</initialHeapSize>
    <maxHeapSize>384</maxHeapSize>
    <opt>-Djava.library.path=swt-win</opt>
  </jre>
</launch4jConfig>